{
  "method": "Relationship-Aware Deterministic Layout",
  "room": {
    "width": 800,
    "height": 600
  },
  "furniture": [
    {
      "name": "Bed",
      "x": 600,
      "y": 420,
      "rotation": 270,
      "width": 180,
      "height": 200
    },
    {
      "name": "Wardrobe",
      "x": 600,
      "y": 305.0,
      "rotation": 0,
      "width": 150,
      "height": 60
    },
    {
      "name": "Wardrobe",
      "x": 600,
      "y": 305.0,
      "rotation": 0,
      "width": 150,
      "height": 60
    },
    {
      "name": "Bedside Table",
      "x": 0,
      "y": 405,
      "rotation": 0,
      "width": 45,
      "height": 45
    },
    {
      "name": "Sofa",
      "x": 710,
      "y": 0,
      "rotation": 270,
      "width": 200,
      "height": 90
    },
    {
      "name": "Sofa",
      "x": 710,
      "y": 0,
      "rotation": 270,
      "width": 200,
      "height": 90
    },
    {
      "name": "Study Table",
      "x": 200,
      "y": 0,
      "rotation": 0,
      "width": 120,
      "height": 70
    },
    {
      "name": "Study Chair",
      "x": 375,
      "y": 550,
      "rotation": 0,
      "width": 50,
      "height": 50
    }
  ],
  "openings": [
    {
      "type": "door",
      "wall": "bottom",
      "position": 377,
      "size": 90,
      "openingHeight": "210"
    },
    {
      "type": "window",
      "wall": "left",
      "position": 193,
      "size": 120,
      "openingHeight": "100",
      "heightFromGround": "90"
    },
    {
      "type": "window",
      "wall": "right",
      "position": 217,
      "size": 120,
      "openingHeight": "100",
      "heightFromGround": "90"
    }
  ],
  "features": [
    "Functional relationship optimization",
    "Wheelchair accessibility compliance",
    "Deterministic and repeatable results",
    "Zone-based furniture grouping",
    "Partner-aware placement"
  ],
  "note": "Optimized layout variation 3"
}